{
 "name": "The Caverns",
 "theme": {
  "w": "ü™®",
  "wall": "rgba(96,96,128,0.38)",
  "back": "#0e0e18",
  "spot": "#e0e0f4"
 },
 "M": [
  "w w   w w w w w w w w ",
  "w d‚Üì    w   d‚à©    w w ",
  "w   w   w   w w     l2",
  "w d‚åøw         w   w w ",
  "w   w w w w   w     w ",
  "w     d‚àßw d=    w   w ",
  "w w w   w   w   w   w ",
  "w m‚âÝ        w       w ",
  "    w w w d‚à®w m‚åΩw d‚åàw ",
  "w               w d‚åäw ",
  "w w w w w w w w w w w "
 ],
 "d‚Üì": {
  "req": "",
  "add": "",
  "task": "{d‚Üì} is the _ruby rune of dropping_, casting away from the start of the list on its right as many items as the number on its left. A rockfall has buried the first `n` runes of the vein `v` ‚Äî recite what still shows.",
  "expr": "(n‚Üê2)‚Üìv‚Üê'STALAGMITE'"
 },
 "d‚à©": {
  "req": "",
  "add": "",
  "task": "{d‚à©} is the _ruby rune of commonality_, keeping (in order) the items on its left that also appear on its right. Which runes of the inscription `i` are echoed in the warding word `w`?",
  "expr": "(i‚Üê'DRAKE MALLARD')‚à©w‚Üê'DARK'"
 },
 "d‚åä": {
  "req": "",
  "add": "",
  "task": "{d‚åä} is the _ruby rune of the lesser_, giving the smaller of each pair it stands between. A vaulted ceiling of `c` caps the crystal heights `h`; no crystal may rise above it.",
  "expr": "(c‚Üê7)‚åäh‚Üê?‚ç®9"
 },
 "d‚åà": {
  "req": "",
  "add": "",
  "task": "{d‚åà} is the _ruby rune of the greater_, giving the larger of each pair it stands between. A risen floor of `f` lifts the crystal heights `h`; none may sink below it.",
  "expr": "(f‚Üê3)‚åàh‚Üê?‚ç®9"
 },
 "d‚åø": {
  "req": "",
  "add": "",
  "task": "{d‚åø} is the _ruby rune of copying_, repeating each item on its right as many times as the matching count on its left. Sound the runes `r`, each echoing by its count in `c`.",
  "expr": "(c‚Üê2 0 3 1 2 3)‚åør‚Üê'DYALOG'"
 },
 "d=": {
  "req": "",
  "add": "",
  "task": "{d=} is the _ruby rune of equality_, marking 1 where its left and right agree and 0 where they differ. Where do the twin tallies `a` and `b` match?",
  "expr": "(a‚Üê3 1 4 1 5)=b‚Üê2 1 4 1 3"
 },
 "m‚âÝ": {
  "req": "",
  "add": "",
  "task": "{m‚âÝ} is the _emerald rune of first sightings_, marking each item of the list on its right that has not been seen earlier in it. Mark the first appearance of every rune in the chant `c`.",
  "expr": "‚âÝc‚Üê'BOOKKEEPER'"
 },
 "d‚àß": {
  "req": "",
  "add": "",
  "task": "{d‚àß} is the _ruby rune of conjunction_, kindling a light only where both its sides are lit. Where are both the wards `a` and `b` aglow at once?",
  "expr": "(a‚Üê1 1 0 0)‚àßb‚Üê0 1 0 1"
 },
 "d‚à®": {
  "req": "",
  "add": "",
  "task": "{d‚à®} is the _ruby rune of disjunction_, kindling a light where either of its sides is lit. Where is either ward `a` or `b` aglow?",
  "expr": "(a‚Üê1 1 0 0)‚à®b‚Üê0 1 0 1"
 },
 "m‚åΩ": {
  "req": "",
  "add": "",
  "task": "{m‚åΩ} is the _emerald rune of reversal_, mirroring the order of the list on its right. The watchtowers along the shore report their heights as `h`; recite them from last to first.",
  "expr": "‚åΩh‚Üê5?99"
 },
 "l2": {
  "req": "d‚åäd‚åàm‚åΩ",
  "add": "",
  "task": "A slab of granite seals the eastern tunnel, scored with a warden's demand: take the crystal readings `r`, let none sink beneath the floor `f` nor rise above the ceiling `c`, then recite them from last to first. Speak them so and the slab grinds aside.",
  "expr": "‚åΩ(f‚Üê3)‚åà(c‚Üê7)‚åär‚Üê?‚ç®9"
 }
}
